LICENSE
README.md
setup.py
/home/jiarui/code/Mask2Former/mask2former/modeling/pixel_decoder/ops/src/vision.cpp
/home/jiarui/code/Mask2Former/mask2former/modeling/pixel_decoder/ops/src/cpu/ms_deform_attn_cpu.cpp
/home/jiarui/code/Mask2Former/mask2former/modeling/pixel_decoder/ops/src/cuda/ms_deform_attn_cuda.cu
mask2former/__init__.py
mask2former/config.py
mask2former/maskformer_model.py
mask2former/test_time_augmentation.py
mask2former/data/__init__.py
mask2former/data/dataset_mappers/__init__.py
mask2former/data/dataset_mappers/coco_instance_new_baseline_dataset_mapper.py
mask2former/data/dataset_mappers/coco_panoptic_new_baseline_dataset_mapper.py
mask2former/data/dataset_mappers/mask_former_instance_dataset_mapper.py
mask2former/data/dataset_mappers/mask_former_panoptic_dataset_mapper.py
mask2former/data/dataset_mappers/mask_former_semantic_dataset_mapper.py
mask2former/data/datasets/__init__.py
mask2former/data/datasets/register_ade20k_full.py
mask2former/data/datasets/register_ade20k_instance.py
mask2former/data/datasets/register_ade20k_panoptic.py
mask2former/data/datasets/register_coco_panoptic_annos_semseg.py
mask2former/data/datasets/register_coco_stuff_10k.py
mask2former/data/datasets/register_mapillary_vistas.py
mask2former/data/datasets/register_mapillary_vistas_panoptic.py
mask2former/evaluation/__init__.py
mask2former/evaluation/instance_evaluation.py
mask2former/modeling/__init__.py
mask2former/modeling/criterion.py
mask2former/modeling/matcher.py
mask2former/modeling/backbone/__init__.py
mask2former/modeling/backbone/swin.py
mask2former/modeling/meta_arch/__init__.py
mask2former/modeling/meta_arch/mask_former_head.py
mask2former/modeling/meta_arch/per_pixel_baseline.py
mask2former/modeling/pixel_decoder/__init__.py
mask2former/modeling/pixel_decoder/fpn.py
mask2former/modeling/pixel_decoder/msdeformattn.py
mask2former/modeling/pixel_decoder/ops/__init__.py
mask2former/modeling/pixel_decoder/ops/test.py
maskformer2.egg-info/PKG-INFO
maskformer2.egg-info/SOURCES.txt
maskformer2.egg-info/dependency_links.txt
maskformer2.egg-info/requires.txt
maskformer2.egg-info/top_level.txt